kinetimail/__init__.py
kinetimail/kinetimail.py
kinetimail-0.1.2.dist-info/licenses/LICENSE
kinetimail-0.1.2.dist-info/METADATA
kinetimail-0.1.2.dist-info/WHEEL
kinetimail-0.1.2.dist-info/top_level.txt
kinetimail-0.1.2.dist-info/RECORD
