Metadata-Version: 2.4
Name: kinetimail
Version: 0.1.2
Summary: Python client for KinetiMail service.
Author: KinetiMail
License: MIT License
Project-URL: Homepage, https://kinetimail.com
Requires-Python: >=3.7
License-File: LICENSE
Requires-Dist: requests>=2.0.0
Dynamic: license-file
